src/__init__.py
src/main.py
mistral_cli_tool-0.1.0.dist-info/METADATA
mistral_cli_tool-0.1.0.dist-info/WHEEL
mistral_cli_tool-0.1.0.dist-info/entry_points.txt
mistral_cli_tool-0.1.0.dist-info/top_level.txt
mistral_cli_tool-0.1.0.dist-info/RECORD
