Metadata-Version: 2.4
Name: mistral_cli_tool
Version: 0.1.0
Summary: A package to call the Mistral AI API
Requires-Python: >=3.6
Requires-Dist: click
Requires-Dist: python-dotenv
Requires-Dist: mistralai
